discord_emojis/__init__.py
discord_emojis/_version.py
discord_emojis/emojis_collection.py
discord_emojis/py.typed
discord_emojis/utils.py
discord_emojis-2024.12.17.dist-info/LICENSE
discord_emojis-2024.12.17.dist-info/METADATA
discord_emojis-2024.12.17.dist-info/WHEEL
discord_emojis-2024.12.17.dist-info/top_level.txt
discord_emojis-2024.12.17.dist-info/RECORD
