Metadata-Version: 2.1
Name: discord_emojis
Version: 2024.12.17
Summary: An up-to-date collection of all valid Discord emojis
Home-page: https://github.com/davfsa/discord_emojis
Author: davfsa
Author-email: davfsa@hikari-py.dev
License: MIT
Project-URL: Source (GitHub), https://github.com/davfsa/discord_emojis
Project-URL: Discord, https://discord.gg/hikari
Project-URL: Issue Tracker, https://github.com/davfsa/discord_emojis/issues
Project-URL: CI, https://github.com/davfsa/discord_emojis/actions
Classifier: Development Status :: 5 - Production/Stable
Classifier: Intended Audience :: Developers
Classifier: License :: OSI Approved :: MIT License
Classifier: Natural Language :: English
Classifier: Operating System :: OS Independent
Classifier: Topic :: Utilities
Classifier: Typing :: Typed
Requires-Python: >=3.8
License-File: LICENSE
